pylogicalprograms/__init__.py
pylogicalprograms/logical/__init__.py
pylogicalprograms/logical/armstrongnumber.py
pylogicalprograms/logical/binarysearch.py
pylogicalprograms/logical/factorial.py
pylogicalprograms/logical/fibonacciseries.py
pylogicalprograms/logical/integertoroman.py
pylogicalprograms/logical/linearsearch.py
pylogicalprograms/logical/missingnumber.py
pylogicalprograms/logical/multiplicationtable.py
pylogicalprograms/logical/numberdigitcount.py
pylogicalprograms/logical/numberofisland.py
pylogicalprograms/logical/numbertoword.py
pylogicalprograms/logical/parentheses.py
pylogicalprograms/logical/permutations.py
pylogicalprograms/logical/reverseinteger.py
pylogicalprograms/logical/romantointeger.py
pylogicalprograms/logical/spiralmatrix.py
pylogicalprograms/logical/stringnumberevaluation.py
pylogicalprograms/logical/stringreverseandpalindrome.py
pylogicalprograms/logical/swaptwonumbers.py
pylogicalprograms/logical/testjustification.py
pylogicalprograms/logical/zigzagconvertion.py
pylogicalprograms/patterns/Alphabetspatterns.py
pylogicalprograms/patterns/DineshNamePattern.py
pylogicalprograms/patterns/NumbersPattern.py
pylogicalprograms/patterns/Pypatterns.py
pylogicalprograms/patterns/__init__.py
pylogicalprograms/shift/__init__.py
pylogicalprograms/shift/leftShift.py
pylogicalprograms/shift/rightShift.py
pylogicalprograms-1.3.dist-info/LICENSE.txt
pylogicalprograms-1.3.dist-info/METADATA
pylogicalprograms-1.3.dist-info/WHEEL
pylogicalprograms-1.3.dist-info/top_level.txt
pylogicalprograms-1.3.dist-info/RECORD
